aib2ofx/__init__.py
aib2ofx/aib.py
aib2ofx/cfg.py
aib2ofx/cli.py
aib2ofx/ofx.py
aib2ofx-0.74.1.dist-info/WHEEL
aib2ofx-0.74.1.dist-info/entry_points.txt
aib2ofx-0.74.1.dist-info/METADATA
aib2ofx-0.74.1.dist-info/RECORD
