Metadata-Version: 2.4
Name: aib2ofx
Version: 0.74.1
Summary: Download data from aib.ie in OFX format
Author: Jakub Turski
Author-email: Jakub Turski <yacoob@gmail.com>
License-Expression: MIT
Requires-Dist: mechanicalsoup~=1.4
Requires-Dist: python-dateutil>=2.9.0,<3
Requires-Python: >=3.11
Project-URL: Repository, https://github.com/yacoob/aib2ofx
